XStatic_smart_table-1.4.13.2-py2.7-nspkg.pth
XStatic_smart_table-1.4.13.2.dist-info/DESCRIPTION.rst
XStatic_smart_table-1.4.13.2.dist-info/METADATA
XStatic_smart_table-1.4.13.2.dist-info/RECORD
XStatic_smart_table-1.4.13.2.dist-info/WHEEL
XStatic_smart_table-1.4.13.2.dist-info/metadata.json
XStatic_smart_table-1.4.13.2.dist-info/namespace_packages.txt
XStatic_smart_table-1.4.13.2.dist-info/top_level.txt
xstatic/pkg/angular_smart_table/__init__.py
xstatic/pkg/angular_smart_table/data/smart-table.js
