Metadata-Version: 2.0
Name: XStatic-smart-table
Version: 1.4.13.2
Summary: smart-table 1.4.13 (XStatic packaging standard)
Home-page: https://github.com/lorenzofox3/Smart-Table
Author: Richard Jones
Author-email: r1chardj0n3s@gmail.com
License: (same as smart-table)
Keywords: smart-table angular table angular_smart_table xstatic
Platform: any
